sql_tstring-0.4.0.dist-info/METADATA
sql_tstring-0.4.0.dist-info/WHEEL
sql_tstring-0.4.0.dist-info/entry_points.txt
sql_tstring-0.4.0.dist-info/licenses/LICENSE
sql_tstring/__init__.py
sql_tstring/parser.py
sql_tstring/py.typed
sql_tstring/t.py
sql_tstring-0.4.0.dist-info/RECORD
