Metadata-Version: 2.4
Name: sql-tstring
Version: 0.4.0
Summary: SQL builder via string templates
Author-Email: pgjones <philip.graham.jones@googlemail.com>
License-Expression: MIT
License-File: LICENSE
Classifier: Development Status :: 3 - Alpha
Classifier: Intended Audience :: Developers
Classifier: Operating System :: OS Independent
Classifier: Programming Language :: Python
Classifier: Programming Language :: Python :: 3
Classifier: Programming Language :: Python :: 3.12
Classifier: Programming Language :: Python :: 3.13
Classifier: Programming Language :: Python :: 3.14
Classifier: Topic :: Software Development :: Libraries :: Python Modules
Requires-Python: >=3.12
Provides-Extra: docs
Requires-Dist: pydata_sphinx_theme; extra == "docs"
